README.md
setup.py
src/anita/__init__.py
src/anita/__main__.py
src/anita/anita_en.py
src/anita/anita_en_basic_usage.py
src/anita/anita_en_fo.py
src/anita/anita_en_gui.py
src/anita/anita_pt.py
src/anita/anita_pt_basic_usage.py
src/anita/anita_pt_fo.py
src/anita/anita_pt_gui.py
src/anita/example_theorems.py
src/anita.egg-info/PKG-INFO
src/anita.egg-info/SOURCES.txt
src/anita.egg-info/dependency_links.txt
src/anita.egg-info/entry_points.txt
src/anita.egg-info/requires.txt
src/anita.egg-info/top_level.txt